versatile/__init__.py
versatile/main.py
versatile-0.0.1a1.dist-info/LICENSE
versatile-0.0.1a1.dist-info/METADATA
versatile-0.0.1a1.dist-info/WHEEL
versatile-0.0.1a1.dist-info/top_level.txt
versatile-0.0.1a1.dist-info/RECORD
